connect_mysql/Connector.py
connect_mysql/__init__.py
connect_mysql/connect_via_bastion.py
connect_mysql/connect_via_bation.py
connect_mysql-0.0.5.dist-info/METADATA
connect_mysql-0.0.5.dist-info/WHEEL
connect_mysql-0.0.5.dist-info/top_level.txt
connect_mysql-0.0.5.dist-info/RECORD
